[{"name":["Kasza z dynią, jarmużem i pomidorami"],"recipe":["1. Kaszę ugotuj według przepisu na opakowaniu.\n2. Dynię obierz, pokrój w kostkę i ugotuj w niewielkiej ilości wody, następnie odcedź.\n3. Pokrój drobno jarmuż i suszone pomidory i podsmaż na oleju kokosowym.\n4. Dodaj ugotowaną kaszę oraz dynię i sezam. Dopraw solą i pieprzem, wymieszaj.\n5. Przed podaniem dodaj pomidorki przekrojone na pół oraz posiekaną pietruszkę."],"hasReplacement":[false],"isPortioned":[false],"ingredients":[{"name":["Kasza jaglana"],"measurements":[{"amount":[3],"unit":["table spoon"],"text":["%s łyżki"],"__typename":["DietProductMeasurement"]},{"amount":[39],"unit":["g"],"text":["%s g"],"__typename":["DietProductMeasurement"]}]},{"name":["Dynia"],"measurements":[{"amount":[1],"unit":["glass"],"text":["%s szklanka"],"__typename":["DietProductMeasurement"]},{"amount":[140],"unit":["g"],"text":["%s g"],"__typename":["DietProductMeasurement"]}]},{"name":["Jarmuż"],"measurements":[{"amount":[3],"unit":["handful"],"text":["%s garście"],"__typename":["DietProductMeasurement"]},{"amount":[60],"unit":["g"],"text":["%s g"],"__typename":["DietProductMeasurement"]}]},{"name":["Suszone pomidory"],"measurements":[{"amount":[3],"unit":["slice"],"text":["%s plastry"],"__typename":["DietProductMeasurement"]},{"amount":[21],"unit":["g"],"text":["%s g"],"__typename":["DietProductMeasurement"]}]},{"name":["Pomidorki koktajlowe"],"measurements":[{"amount":[8],"unit":["piece"],"text":["%s sztuk"],"__typename":["DietProductMeasurement"]},{"amount":[160],"unit":["g"],"text":["%s g"],"__typename":["DietProductMeasurement"]}]},{"name":["Olej kokosowy extra virgin"],"measurements":[{"amount":[0.66],"unit":["spoon"],"text":["%s łyżeczki"],"__typename":["DietProductMeasurement"]},{"amount":[10],"unit":["g"],"text":["%s g"],"__typename":["DietProductMeasurement"]}]},{"name":["Sezam nasiona"],"measurements":[{"amount":[1],"unit":["spoon"],"text":["%s łyżeczka"],"__typename":["DietProductMeasurement"]},{"amount":[5],"unit":["g"],"text":["%s g"],"__typename":["DietProductMeasurement"]}]},{"name":["Pietruszka liście"],"measurements":[{"amount":[1],"unit":["spoon"],"text":["%s łyżeczka"],"__typename":["DietProductMeasurement"]},{"amount":[6],"unit":["g"],"text":["%s g"],"__typename":["DietProductMeasurement"]}]},{"name":["Sól morska"],"measurements":[{"amount":[0.25],"unit":["spoon"],"text":["%s łyżeczki"],"__typename":["DietProductMeasurement"]},{"amount":[2],"unit":["g"],"text":["%s g"],"__typename":["DietProductMeasurement"]}]},{"name":["Pieprz czarny"],"measurements":[{"amount":[2],"unit":["pinch"],"text":["%s szczypty"],"__typename":["DietProductMeasurement"]}]}]}]
