[{"name":["Kotlety wołowe"],"recipe":["1. Cebulę i czosnek drobno posiekaj. \n2. Na patelni rozgrzej tłuszcz i podsmaż cebulę z czosnkiem. \n3. Mięso wymieszaj z jajkiem, cebulą, czosnkiem i przyprawami. \n4. Uformuj burgery i piecz w 200°C przez około 25 minut."],"hasReplacement":[false],"isPortioned":[false],"ingredients":[{"name":["Cebula"],"measurements":[{"amount":[0.25],"unit":["piece"],"text":["%s sztuki"],"__typename":["DietProductMeasurement"]},{"amount":[28],"unit":["g"],"text":["%s g"],"__typename":["DietProductMeasurement"]}]},{"name":["Czosnek"],"measurements":[{"amount":[0.5],"unit":["clove"],"text":["%s ząbka"],"__typename":["DietProductMeasurement"]},{"amount":[3],"unit":["g"],"text":["%s g"],"__typename":["DietProductMeasurement"]}]},{"name":["Masło klarowane"],"measurements":[{"amount":[0.5],"unit":["spoon"],"text":["%s łyżeczki"],"__typename":["DietProductMeasurement"]},{"amount":[4],"unit":["g"],"text":["%s g"],"__typename":["DietProductMeasurement"]}]},{"name":["Wołowina rostbef"],"measurements":[{"amount":[110],"unit":["g"],"text":["%s g"],"__typename":["DietProductMeasurement"]}]},{"name":["Jaja kurze małe, rozmiar S"],"measurements":[{"amount":[1],"unit":["piece"],"text":["%s sztuka"],"__typename":["DietProductMeasurement"]},{"amount":[50],"unit":["g"],"text":["%s g"],"__typename":["DietProductMeasurement"]}]},{"name":["Sól morska"],"measurements":[{"amount":[1],"unit":["pinch"],"text":["%s szczypta"],"__typename":["DietProductMeasurement"]}]},{"name":["Pieprz czarny"],"measurements":[{"amount":[1],"unit":["pinch"],"text":["%s szczypta"],"__typename":["DietProductMeasurement"]}]},{"name":["Tymianek suszony"],"measurements":[{"amount":[1],"unit":["pinch"],"text":["%s szczypta"],"__typename":["DietProductMeasurement"]}]},{"name":["Oregano suszone"],"measurements":[{"amount":[1],"unit":["pinch"],"text":["%s szczypta"],"__typename":["DietProductMeasurement"]}]},{"name":["Kurkuma mielona"],"measurements":[{"amount":[1],"unit":["pinch"],"text":["%s szczypta"],"__typename":["DietProductMeasurement"]}]}]}]
