[{"name":["Omlet z brokułami"],"recipe":["1. Brokuły podziel na drobne różyczki, czosnek drobno posiekaj. \n2. Na patelni rozgrzej tłuszcz i podsmaż czosnek. \n3. Dodaj brokuły i smaż przez 2-3 minuty. \n4. Jaja wymieszaj z mąką, mlekiem roślinnym i przyprawami. \n5. Masę jajeczną wlej na patelnię i smaż omlet z dwóch stron."],"hasReplacement":[false],"isPortioned":[false],"ingredients":[{"name":["Brokuły"],"measurements":[{"amount":[0.25],"unit":["piece"],"text":["%s sztuki"],"__typename":["DietProductMeasurement"]},{"amount":[125],"unit":["g"],"text":["%s g"],"__typename":["DietProductMeasurement"]}]},{"name":["Czosnek"],"measurements":[{"amount":[0.5],"unit":["clove"],"text":["%s ząbka"],"__typename":["DietProductMeasurement"]},{"amount":[3],"unit":["g"],"text":["%s g"],"__typename":["DietProductMeasurement"]}]},{"name":["Olej kokosowy extra virgin"],"measurements":[{"amount":[0.33],"unit":["table spoon"],"text":["%s łyżki"],"__typename":["DietProductMeasurement"]},{"amount":[9],"unit":["g"],"text":["%s g"],"__typename":["DietProductMeasurement"]}]},{"name":["Jaja kurze małe, rozmiar S"],"measurements":[{"amount":[2],"unit":["piece"],"text":["%s sztuki"],"__typename":["DietProductMeasurement"]},{"amount":[100],"unit":["g"],"text":["%s g"],"__typename":["DietProductMeasurement"]}]},{"name":["Mąka kokosowa odtłuszczona"],"measurements":[{"amount":[2],"unit":["table spoon"],"text":["%s łyżki"],"__typename":["DietProductMeasurement"]},{"amount":[26],"unit":["g"],"text":["%s g"],"__typename":["DietProductMeasurement"]}]},{"name":["Mleko migdałowe"],"measurements":[{"amount":[4],"unit":["table spoon"],"text":["%s łyżki"],"__typename":["DietProductMeasurement"]},{"amount":[40],"unit":["ml"],"text":["%s ml"],"__typename":["DietProductMeasurement"]}]},{"name":["Sól morska"],"measurements":[{"amount":[1],"unit":["pinch"],"text":["%s szczypta"],"__typename":["DietProductMeasurement"]}]},{"name":["Pieprz czarny"],"measurements":[{"amount":[1],"unit":["pinch"],"text":["%s szczypta"],"__typename":["DietProductMeasurement"]}]}]}]
