[{"name":["Podsmażane pieczarki"],"recipe":["1. Pieczarki pokrój w ćwiartki i wrzuć na rozgrzane masło.\n2. Smaż kilka minut, dopraw solą i pieprzem."],"hasReplacement":[false],"isPortioned":[false],"ingredients":[{"name":["Pieczarka uprawna świeża"],"measurements":[{"amount":[4],"unit":["piece"],"text":["%s sztuki"],"__typename":["DietProductMeasurement"]},{"amount":[80],"unit":["g"],"text":["%s g"],"__typename":["DietProductMeasurement"]}]},{"name":["Masło klarowane"],"measurements":[{"amount":[0.33],"unit":["spoon"],"text":["%s łyżeczki"],"__typename":["DietProductMeasurement"]},{"amount":[3],"unit":["g"],"text":["%s g"],"__typename":["DietProductMeasurement"]}]},{"name":["Sól morska"],"measurements":[{"amount":[1],"unit":["pinch"],"text":["%s szczypta"],"__typename":["DietProductMeasurement"]}]},{"name":["Pieprz czarny"],"measurements":[{"amount":[1],"unit":["pinch"],"text":["%s szczypta"],"__typename":["DietProductMeasurement"]}]}]}]
