[{"name":["Praliny śliwka w czekoladzie"],"recipe":["1. Owoce suszone zalej wrzątkiem i odstaw na 10-20 minut.\n2. Orzechy laskowe i migdały zmiel na \"mąkę\".\n3. Dodaj do niej wcześniej namoczone owoce, połowę kakao i wodę. Zmiksuj na kleistą masę.\n4. Z powstałej masy ulep małe kuleczki, obtocz je w pozostałym kakao i wstaw na 15-20 minut do lodówki."],"hasReplacement":[false],"isPortioned":[true],"ingredients":[{"name":["Orzechy laskowe"],"measurements":[{"amount":[1],"unit":["handful"],"text":["%s garść"],"__typename":["DietProductMeasurement"]},{"amount":[30],"unit":["g"],"text":["%s g"],"__typename":["DietProductMeasurement"]}]},{"name":["Migdały"],"measurements":[{"amount":[1],"unit":["handful"],"text":["%s garść"],"__typename":["DietProductMeasurement"]},{"amount":[30],"unit":["g"],"text":["%s g"],"__typename":["DietProductMeasurement"]}]},{"name":["Daktyle suszone niesiarkowane"],"measurements":[{"amount":[0.66],"unit":["handful"],"text":["%s garści"],"__typename":["DietProductMeasurement"]},{"amount":[30],"unit":["g"],"text":["%s g"],"__typename":["DietProductMeasurement"]}]},{"name":["Śliwki suszone"],"measurements":[{"amount":[0.5],"unit":["handful"],"text":["%s garści"],"__typename":["DietProductMeasurement"]},{"amount":[30],"unit":["g"],"text":["%s g"],"__typename":["DietProductMeasurement"]}]},{"name":["Kakao gorzkie"],"measurements":[{"amount":[1],"unit":["table spoon"],"text":["%s łyżka"],"__typename":["DietProductMeasurement"]},{"amount":[10],"unit":["g"],"text":["%s g"],"__typename":["DietProductMeasurement"]}]},{"name":["Woda"],"measurements":[{"amount":[1],"unit":["table spoon"],"text":["%s łyżka"],"__typename":["DietProductMeasurement"]},{"amount":[15],"unit":["ml"],"text":["%s ml"],"__typename":["DietProductMeasurement"]}]}]}]
