[{"name":["Ryba w sosie pomidorowym z oliwkami"],"recipe":["1. Cebulę i czosnek drobno posiekaj. \n2. Na patelni rozgrzej tłuszcz i podsmaż cebulę z czosnkiem. \n3. Dodaj rybę, pomidory, pokrojone w plasterki oliwki, zioła i przyprawy. \n4. Duś pod przykryciem przez około 15-20 minut."],"hasReplacement":[false],"isPortioned":[false],"ingredients":[{"name":["Cebula"],"measurements":[{"amount":[0.5],"unit":["piece"],"text":["%s sztuki"],"__typename":["DietProductMeasurement"]},{"amount":[55],"unit":["g"],"text":["%s g"],"__typename":["DietProductMeasurement"]}]},{"name":["Czosnek"],"measurements":[{"amount":[1],"unit":["clove"],"text":["%s ząbek"],"__typename":["DietProductMeasurement"]},{"amount":[5],"unit":["g"],"text":["%s g"],"__typename":["DietProductMeasurement"]}]},{"name":["Olej kokosowy extra virgin"],"measurements":[{"amount":[0.5],"unit":["spoon"],"text":["%s łyżeczki"],"__typename":["DietProductMeasurement"]},{"amount":[8],"unit":["g"],"text":["%s g"],"__typename":["DietProductMeasurement"]}]},{"name":["Dorsz świeży filety bez skóry"],"measurements":[{"amount":[150],"unit":["g"],"text":["%s g"],"__typename":["DietProductMeasurement"]}]},{"name":["Pomidory krojone w sosie własnym"],"measurements":[{"amount":[0.66],"unit":["glass"],"text":["%s szklanki"],"__typename":["DietProductMeasurement"]},{"amount":[160],"unit":["g"],"text":["%s g"],"__typename":["DietProductMeasurement"]}]},{"name":["Oliwki czarne marynowane"],"measurements":[{"amount":[8],"unit":["piece"],"text":["%s sztuk"],"__typename":["DietProductMeasurement"]},{"amount":[20],"unit":["g"],"text":["%s g"],"__typename":["DietProductMeasurement"]}]},{"name":["Bazylia świeża"],"measurements":[{"amount":[2],"unit":["leaf"],"text":["%s liście"],"__typename":["DietProductMeasurement"]},{"amount":[2],"unit":["g"],"text":["%s g"],"__typename":["DietProductMeasurement"]}]},{"name":["Estragon suszony"],"measurements":[{"amount":[1],"unit":["pinch"],"text":["%s szczypta"],"__typename":["DietProductMeasurement"]}]},{"name":["Tymianek suszony"],"measurements":[{"amount":[1],"unit":["pinch"],"text":["%s szczypta"],"__typename":["DietProductMeasurement"]}]},{"name":["Sól morska"],"measurements":[{"amount":[1],"unit":["pinch"],"text":["%s szczypta"],"__typename":["DietProductMeasurement"]}]},{"name":["Pieprz czarny"],"measurements":[{"amount":[1],"unit":["pinch"],"text":["%s szczypta"],"__typename":["DietProductMeasurement"]}]}]}]
