[{"name":["Sałatka z grillowanym kurczakiem"],"recipe":["1, Kurczaka przypraw i grilluj, a następnie pokrój w kostkę.\n2. Pomidorki przekrój na pół, a ogórka pokrój w kostkę. \n3. Na talerzu układaj sałatę, pomidorki, ogórka i kurczaka.\n4. Skrop sokiem z cytryny."],"hasReplacement":[false],"isPortioned":[false],"ingredients":[{"name":["Mięso z piersi kurczaka bez skóry"],"measurements":[{"amount":[150],"unit":["g"],"text":["%s g"],"__typename":["DietProductMeasurement"]}]},{"name":["Sałata lodowa"],"measurements":[{"amount":[2],"unit":["leaf"],"text":["%s liście"],"__typename":["DietProductMeasurement"]},{"amount":[80],"unit":["g"],"text":["%s g"],"__typename":["DietProductMeasurement"]}]},{"name":["Pomidorki koktajlowe"],"measurements":[{"amount":[5],"unit":["piece"],"text":["%s sztuk"],"__typename":["DietProductMeasurement"]},{"amount":[100],"unit":["g"],"text":["%s g"],"__typename":["DietProductMeasurement"]}]},{"name":["Ogórek kiszony"],"measurements":[{"amount":[1],"unit":["piece"],"text":["%s sztuka"],"__typename":["DietProductMeasurement"]},{"amount":[60],"unit":["g"],"text":["%s g"],"__typename":["DietProductMeasurement"]}]},{"name":["Sok wyciśnięty z cytryny"],"measurements":[{"amount":[1],"unit":["spoon"],"text":["%s łyżeczka"],"__typename":["DietProductMeasurement"]},{"amount":[3],"unit":["g"],"text":["%s g"],"__typename":["DietProductMeasurement"]}]},{"name":["Zioła prowansalskie"],"measurements":[{"amount":[1],"unit":["pinch"],"text":["%s szczypta"],"__typename":["DietProductMeasurement"]}]},{"name":["Pieprz czarny"],"measurements":[{"amount":[1],"unit":["pinch"],"text":["%s szczypta"],"__typename":["DietProductMeasurement"]}]},{"name":["Sól himalajska"],"measurements":[{"amount":[1],"unit":["pinch"],"text":["%s szczypta"],"__typename":["DietProductMeasurement"]}]}]}]
