[{"name":["Smoothie gruszka-kiwi"],"recipe":["1. Owoce obierz i pokrój na kawałki.\n2. Zblenduj składniki z dodatkiem soku jabłkowego."],"hasReplacement":[false],"isPortioned":[false],"ingredients":[{"name":["Gruszka"],"measurements":[{"amount":[1],"unit":["piece"],"text":["%s sztuka"],"__typename":["DietProductMeasurement"]},{"amount":[130],"unit":["g"],"text":["%s g"],"__typename":["DietProductMeasurement"]}]},{"name":["Kiwi"],"measurements":[{"amount":[2],"unit":["piece"],"text":["%s sztuki"],"__typename":["DietProductMeasurement"]},{"amount":[150],"unit":["g"],"text":["%s g"],"__typename":["DietProductMeasurement"]}]},{"name":["Pietruszka liście"],"measurements":[{"amount":[1],"unit":["spoon"],"text":["%s łyżeczka"],"__typename":["DietProductMeasurement"]},{"amount":[6],"unit":["g"],"text":["%s g"],"__typename":["DietProductMeasurement"]}]},{"name":["Nasiona chia"],"measurements":[{"amount":[1],"unit":["spoon"],"text":["%s łyżeczka"],"__typename":["DietProductMeasurement"]},{"amount":[5],"unit":["g"],"text":["%s g"],"__typename":["DietProductMeasurement"]}]},{"name":["Sok jabłkowy, świeżo wyciśnięty"],"measurements":[{"amount":[0.5],"unit":["glass"],"text":["%s szklanki"],"__typename":["DietProductMeasurement"]},{"amount":[115],"unit":["ml"],"text":["%s ml"],"__typename":["DietProductMeasurement"]}]}]}]
